README.md
README.rst
setup.py
torch_text_similarity/__init__.py
torch_text_similarity/learner.py
torch_text_similarity.egg-info/PKG-INFO
torch_text_similarity.egg-info/SOURCES.txt
torch_text_similarity.egg-info/dependency_links.txt
torch_text_similarity.egg-info/requires.txt
torch_text_similarity.egg-info/top_level.txt
torch_text_similarity/data/__init__.py
torch_text_similarity/data/dataset.py
torch_text_similarity/model/__init__.py
torch_text_similarity/model/similarity.py
torch_text_similarity/util/__init__.py
torch_text_similarity/util/download.py
torch_text_similarity/util/processing.py