Metadata-Version: 1.1
Name: torch-text-similarity
Version: 1.0.4
Summary: Implementations of models and metrics for semantic text similarity. Includes fine-tuning and prediction of models
Home-page: https://github.com/tczhangzhi/torch-text-similarity
Author: ZHANG Zack
Author-email: 850734033@qq.com
License: MIT
Platform: UNKNOWN
Classifier: Development Status :: 4 - Beta
Classifier: License :: OSI Approved :: MIT License
Classifier: Programming Language :: Python :: 3.5
Classifier: Natural Language :: English
Classifier: Topic :: Text Processing :: Linguistic
Classifier: Intended Audience :: Science/Research
